[
  {
    "ContainingType": "EVMManagementStore.Controllers.AuthController",
    "Method": "Login",
    "RelativePath": "api/Auth/login",
    "HttpMethod": "POST",
    "IsController": true,
    "Order": 0,
    "Parameters": [
      {
        "Name": "request",
        "Type": "EVMManagementStore.Service.DTO.LoginRequest",
        "IsRequired": true
      }
    ],
    "ReturnTypes": []
  },
  {
    "ContainingType": "EVMManagementStore.Controllers.CustomerController",
    "Method": "GetAll",
    "RelativePath": "api/Customer",
    "HttpMethod": "GET",
    "IsController": true,
    "Order": 0,
    "Parameters": [],
    "ReturnTypes": []
  },
  {
    "ContainingType": "EVMManagementStore.Controllers.CustomerController",
    "Method": "Create",
    "RelativePath": "api/Customer",
    "HttpMethod": "POST",
    "IsController": true,
    "Order": 0,
    "Parameters": [
      {
        "Name": "dto",
        "Type": "EVMManagementStore.Service.DTO.CustomerDTO",
        "IsRequired": true
      }
    ],
    "ReturnTypes": []
  },
  {
    "ContainingType": "EVMManagementStore.Controllers.CustomerController",
    "Method": "GetById",
    "RelativePath": "api/Customer/{id}",
    "HttpMethod": "GET",
    "IsController": true,
    "Order": 0,
    "Parameters": [
      {
        "Name": "id",
        "Type": "System.Int32",
        "IsRequired": true
      }
    ],
    "ReturnTypes": []
  },
  {
    "ContainingType": "EVMManagementStore.Controllers.CustomerController",
    "Method": "Update",
    "RelativePath": "api/Customer/{id}",
    "HttpMethod": "PUT",
    "IsController": true,
    "Order": 0,
    "Parameters": [
      {
        "Name": "id",
        "Type": "System.Int32",
        "IsRequired": true
      },
      {
        "Name": "dto",
        "Type": "EVMManagementStore.Service.DTO.CustomerDTO",
        "IsRequired": true
      }
    ],
    "ReturnTypes": []
  },
  {
    "ContainingType": "EVMManagementStore.Controllers.CustomerController",
    "Method": "Delete",
    "RelativePath": "api/Customer/{id}",
    "HttpMethod": "DELETE",
    "IsController": true,
    "Order": 0,
    "Parameters": [
      {
        "Name": "id",
        "Type": "System.Int32",
        "IsRequired": true
      }
    ],
    "ReturnTypes": []
  },
  {
    "ContainingType": "EVMManagementStore.Controllers.DeliveryController",
    "Method": "GetAll",
    "RelativePath": "api/Delivery",
    "HttpMethod": "GET",
    "IsController": true,
    "Order": 0,
    "Parameters": [],
    "ReturnTypes": []
  },
  {
    "ContainingType": "EVMManagementStore.Controllers.DeliveryController",
    "Method": "Create",
    "RelativePath": "api/Delivery",
    "HttpMethod": "POST",
    "IsController": true,
    "Order": 0,
    "Parameters": [
      {
        "Name": "dto",
        "Type": "EVMManagementStore.Service.DTO.DeliveryDTO",
        "IsRequired": true
      }
    ],
    "ReturnTypes": []
  },
  {
    "ContainingType": "EVMManagementStore.Controllers.DeliveryController",
    "Method": "GetById",
    "RelativePath": "api/Delivery/{id}",
    "HttpMethod": "GET",
    "IsController": true,
    "Order": 0,
    "Parameters": [
      {
        "Name": "id",
        "Type": "System.Int32",
        "IsRequired": true
      }
    ],
    "ReturnTypes": []
  },
  {
    "ContainingType": "EVMManagementStore.Controllers.DeliveryController",
    "Method": "Update",
    "RelativePath": "api/Delivery/{id}",
    "HttpMethod": "PUT",
    "IsController": true,
    "Order": 0,
    "Parameters": [
      {
        "Name": "id",
        "Type": "System.Int32",
        "IsRequired": true
      },
      {
        "Name": "dto",
        "Type": "EVMManagementStore.Service.DTO.DeliveryDTO",
        "IsRequired": true
      }
    ],
    "ReturnTypes": []
  },
  {
    "ContainingType": "EVMManagementStore.Controllers.DeliveryController",
    "Method": "Delete",
    "RelativePath": "api/Delivery/{id}",
    "HttpMethod": "DELETE",
    "IsController": true,
    "Order": 0,
    "Parameters": [
      {
        "Name": "id",
        "Type": "System.Int32",
        "IsRequired": true
      }
    ],
    "ReturnTypes": []
  },
  {
    "ContainingType": "EVMManagementStore.Controllers.PaymentController",
    "Method": "GetAll",
    "RelativePath": "api/Payment",
    "HttpMethod": "GET",
    "IsController": true,
    "Order": 0,
    "Parameters": [],
    "ReturnTypes": []
  },
  {
    "ContainingType": "EVMManagementStore.Controllers.PaymentController",
    "Method": "Create",
    "RelativePath": "api/Payment",
    "HttpMethod": "POST",
    "IsController": true,
    "Order": 0,
    "Parameters": [
      {
        "Name": "dto",
        "Type": "EVMManagementStore.Service.DTO.PaymentDTO",
        "IsRequired": true
      }
    ],
    "ReturnTypes": []
  },
  {
    "ContainingType": "EVMManagementStore.Controllers.PaymentController",
    "Method": "GetById",
    "RelativePath": "api/Payment/{id}",
    "HttpMethod": "GET",
    "IsController": true,
    "Order": 0,
    "Parameters": [
      {
        "Name": "id",
        "Type": "System.Int32",
        "IsRequired": true
      }
    ],
    "ReturnTypes": []
  },
  {
    "ContainingType": "EVMManagementStore.Controllers.PaymentController",
    "Method": "Update",
    "RelativePath": "api/Payment/{id}",
    "HttpMethod": "PUT",
    "IsController": true,
    "Order": 0,
    "Parameters": [
      {
        "Name": "id",
        "Type": "System.Int32",
        "IsRequired": true
      },
      {
        "Name": "dto",
        "Type": "EVMManagementStore.Service.DTO.PaymentDTO",
        "IsRequired": true
      }
    ],
    "ReturnTypes": []
  },
  {
    "ContainingType": "EVMManagementStore.Controllers.PaymentController",
    "Method": "Delete",
    "RelativePath": "api/Payment/{id}",
    "HttpMethod": "DELETE",
    "IsController": true,
    "Order": 0,
    "Parameters": [
      {
        "Name": "id",
        "Type": "System.Int32",
        "IsRequired": true
      }
    ],
    "ReturnTypes": []
  },
  {
    "ContainingType": "EVMManagementStore.Controllers.ReportController",
    "Method": "GetAll",
    "RelativePath": "api/Report",
    "HttpMethod": "GET",
    "IsController": true,
    "Order": 0,
    "Parameters": [],
    "ReturnTypes": []
  },
  {
    "ContainingType": "EVMManagementStore.Controllers.ReportController",
    "Method": "Create",
    "RelativePath": "api/Report",
    "HttpMethod": "POST",
    "IsController": true,
    "Order": 0,
    "Parameters": [
      {
        "Name": "dto",
        "Type": "EVMManagementStore.Service.DTO.ReportDTO",
        "IsRequired": true
      }
    ],
    "ReturnTypes": []
  },
  {
    "ContainingType": "EVMManagementStore.Controllers.ReportController",
    "Method": "GetById",
    "RelativePath": "api/Report/{id}",
    "HttpMethod": "GET",
    "IsController": true,
    "Order": 0,
    "Parameters": [
      {
        "Name": "id",
        "Type": "System.Int32",
        "IsRequired": true
      }
    ],
    "ReturnTypes": []
  },
  {
    "ContainingType": "EVMManagementStore.Controllers.ReportController",
    "Method": "Update",
    "RelativePath": "api/Report/{id}",
    "HttpMethod": "PUT",
    "IsController": true,
    "Order": 0,
    "Parameters": [
      {
        "Name": "id",
        "Type": "System.Int32",
        "IsRequired": true
      },
      {
        "Name": "dto",
        "Type": "EVMManagementStore.Service.DTO.ReportDTO",
        "IsRequired": true
      }
    ],
    "ReturnTypes": []
  },
  {
    "ContainingType": "EVMManagementStore.Controllers.ReportController",
    "Method": "Delete",
    "RelativePath": "api/Report/{id}",
    "HttpMethod": "DELETE",
    "IsController": true,
    "Order": 0,
    "Parameters": [
      {
        "Name": "id",
        "Type": "System.Int32",
        "IsRequired": true
      }
    ],
    "ReturnTypes": []
  },
  {
    "ContainingType": "EVMManagementStore.Controllers.SaleManagementController",
    "Method": "CreateDealerOrder",
    "RelativePath": "api/SaleManagement/CreateDealerOrder",
    "HttpMethod": "POST",
    "IsController": true,
    "Order": 0,
    "Parameters": [
      {
        "Name": "dto",
        "Type": "EVMManagementStore.Service.DTO.DealerOrderDTO",
        "IsRequired": true
      }
    ],
    "ReturnTypes": []
  },
  {
    "ContainingType": "EVMManagementStore.Controllers.SaleManagementController",
    "Method": "CreateOrder",
    "RelativePath": "api/SaleManagement/CreateOrder",
    "HttpMethod": "POST",
    "IsController": true,
    "Order": 0,
    "Parameters": [
      {
        "Name": "dto",
        "Type": "EVMManagementStore.Service.DTO.OrderDTO",
        "IsRequired": true
      }
    ],
    "ReturnTypes": []
  },
  {
    "ContainingType": "EVMManagementStore.Controllers.SaleManagementController",
    "Method": "CreateQuotation",
    "RelativePath": "api/SaleManagement/CreateQuotation",
    "HttpMethod": "POST",
    "IsController": true,
    "Order": 0,
    "Parameters": [
      {
        "Name": "dto",
        "Type": "EVMManagementStore.Service.DTO.QuotationDTO",
        "IsRequired": true
      }
    ],
    "ReturnTypes": []
  },
  {
    "ContainingType": "EVMManagementStore.Controllers.SaleManagementController",
    "Method": "CteateSaleContract",
    "RelativePath": "api/SaleManagement/CreateSaleContract",
    "HttpMethod": "POST",
    "IsController": true,
    "Order": 0,
    "Parameters": [
      {
        "Name": "dto",
        "Type": "EVMManagementStore.Service.DTO.SalesContractDTO",
        "IsRequired": true
      }
    ],
    "ReturnTypes": []
  },
  {
    "ContainingType": "EVMManagementStore.Controllers.TestDriveAppointmentController",
    "Method": "GetAll",
    "RelativePath": "api/TestDriveAppointment",
    "HttpMethod": "GET",
    "IsController": true,
    "Order": 0,
    "Parameters": [],
    "ReturnTypes": []
  },
  {
    "ContainingType": "EVMManagementStore.Controllers.TestDriveAppointmentController",
    "Method": "Create",
    "RelativePath": "api/TestDriveAppointment",
    "HttpMethod": "POST",
    "IsController": true,
    "Order": 0,
    "Parameters": [
      {
        "Name": "dto",
        "Type": "EVMManagementStore.Service.DTO.TestDriveAppointmentDTO",
        "IsRequired": true
      }
    ],
    "ReturnTypes": []
  },
  {
    "ContainingType": "EVMManagementStore.Controllers.TestDriveAppointmentController",
    "Method": "GetById",
    "RelativePath": "api/TestDriveAppointment/{id}",
    "HttpMethod": "GET",
    "IsController": true,
    "Order": 0,
    "Parameters": [
      {
        "Name": "id",
        "Type": "System.Int32",
        "IsRequired": true
      }
    ],
    "ReturnTypes": []
  },
  {
    "ContainingType": "EVMManagementStore.Controllers.TestDriveAppointmentController",
    "Method": "Update",
    "RelativePath": "api/TestDriveAppointment/{id}",
    "HttpMethod": "PUT",
    "IsController": true,
    "Order": 0,
    "Parameters": [
      {
        "Name": "id",
        "Type": "System.Int32",
        "IsRequired": true
      },
      {
        "Name": "dto",
        "Type": "EVMManagementStore.Service.DTO.TestDriveAppointmentDTO",
        "IsRequired": true
      }
    ],
    "ReturnTypes": []
  },
  {
    "ContainingType": "EVMManagementStore.Controllers.TestDriveAppointmentController",
    "Method": "Delete",
    "RelativePath": "api/TestDriveAppointment/{id}",
    "HttpMethod": "DELETE",
    "IsController": true,
    "Order": 0,
    "Parameters": [
      {
        "Name": "id",
        "Type": "System.Int32",
        "IsRequired": true
      }
    ],
    "ReturnTypes": []
  },
  {
    "ContainingType": "EVMManagementStore.Controllers.VehicleController",
    "Method": "GetVehicle",
    "RelativePath": "api/Vehicle",
    "HttpMethod": "GET",
    "IsController": true,
    "Order": 0,
    "Parameters": [],
    "ReturnTypes": []
  },
  {
    "ContainingType": "EVMManagementStore.Controllers.VehicleController",
    "Method": "GetVehicleById",
    "RelativePath": "api/Vehicle/{id}",
    "HttpMethod": "GET",
    "IsController": true,
    "Order": 0,
    "Parameters": [
      {
        "Name": "id",
        "Type": "System.Int32",
        "IsRequired": true
      }
    ],
    "ReturnTypes": []
  },
  {
    "ContainingType": "EVMManagementStore.Controllers.VehicleController",
    "Method": "Compare",
    "RelativePath": "api/Vehicle/CompareCar",
    "HttpMethod": "GET",
    "IsController": true,
    "Order": 0,
    "Parameters": [
      {
        "Name": "vehicleId1",
        "Type": "System.Int32",
        "IsRequired": false
      },
      {
        "Name": "vehicleId2",
        "Type": "System.Int32",
        "IsRequired": false
      }
    ],
    "ReturnTypes": []
  }
]